{"subjects":{"1st":{"CSE":[{"name":"Physics-I","code":"BS-PH101"},{"name":"Mathematics-IA","code":"BS-M101"},{"name":"Basic Electrical Engineering","code":"ES-EE101"}],"IT":[{"name":"Physics-I","code":"BS-PH101"},{"name":"Mathematics-IA","code":"BS-M101"},{"name":"Basic Electrical Engineering","code":"ES-EE101"}],"ECE":[{"name":"Chemistry-I","code":"BS-CH101"},{"name":"Mathematics-IB","code":"BS-M102"},{"name":"Basic Electrical Engineering","code":"ES-EE101"}],"ME":[{"name":"Chemistry-I","code":"BS-CH101"},{"name":"Mathematics-IB","code":"BS-M102"},{"name":"Basic Electrical Engineering","code":"ES-EE101"}],"CSDS":[{"name":"Chemistry-I","code":"BS-CH101"},{"name":"Mathematics-IB","code":"BS-M102"},{"name":"Basic Electrical Engineering","code":"ES-EE101"}],"EE":[{"name":"Chemistry-I","code":"BS-CH101"},{"name":"Mathematics-IB","code":"BS-M102"},{"name":"Basic Electrical Engineering","code":"ES-EE101"}],"AEIE":[{"name":"Chemistry-I","code":"BS-CH101"},{"name":"Mathematics-IB","code":"BS-M102"},{"name":"Basic Electrical Engineering","code":"ES-EE101"}]},"2nd":{"CSE":[{"name":"Chemistry-I","code":"BS-CH201"},{"name":"Mathematics-IIA","code":"BS-M201"},{"name":"Programming for Problem Solving","code":"ES-CS201"},{"name":"English","code":"HM-HU201"}],"IT":[{"name":"Chemistry-I","code":"BS-CH201"},{"name":"Mathematics-IIA","code":"BS-M201"},{"name":"Programming for Problem Solving","code":"ES-CS201"},{"name":"English","code":"HM-HU201"}],"ECE":[{"name":"Physics-I","code":"BS-PH201"},{"name":"Mathematics-IIB","code":"BS-M202"},{"name":"Programming for Problem Solving","code":"ES-CS201"},{"name":"English","code":"HM-HU201"}],"ME":[{"name":"Physics-I","code":"BS-PH201"},{"name":"Mathematics-IIB","code":"BS-M202"},{"name":"Programming for Problem Solving","code":"ES-CS201"},{"name":"English","code":"HM-HU201"}],"CSDS":[{"name":"Physics-I","code":"BS-PH201"},{"name":"Mathematics-IIB","code":"BS-M202"},{"name":"Programming for Problem Solving","code":"ES-CS201"},{"name":"English","code":"HM-HU201"}],"EE":[{"name":"Physics-I","code":"BS-PH201"},{"name":"Mathematics-IIB","code":"BS-M202"},{"name":"Programming for Problem Solving","code":"ES-CS201"},{"name":"English","code":"HM-HU201"}],"AEIE":[{"name":"Physics-I","code":"BS-PH201"},{"name":"Mathematics-IIB","code":"BS-M202"},{"name":"Programming for Problem Solving","code":"ES-CS201"},{"name":"English","code":"HM-HU201"}]},"3rd":{"CSE":[{"name":"Analog and Digital Electronics","code":"ESC 301"},{"name":"Data Structure & Algorithms","code":"PCC-CS301"},{"name":"Computer Organisation","code":"PCC-CS302"},{"name":"Mathematics-III","code":"BSC 301"},{"name":"Economics for Engineers","code":"HSMC 301"}],"IT":[{"name":"Analog and Digital Electronics","code":"ESC 301"},{"name":"Data Structure & Algorithms","code":"PCC-CS301"},{"name":"Computer Organisation","code":"PCC-CS302"},{"name":"Mathematics-III","code":"BSC 301"},{"name":"Economics for Engineers","code":"HSMC 301"}],"ECE":[{"name":"Electronic Devices","code":"EC301"},{"name":"Digital System Design","code":"EC302"},{"name":"Signals and Systems","code":"EC303"},{"name":"Network Theory","code":"EC304"},{"name":"Data Structure & Algorithm","code":"ES-CS301"},{"name":"Probability & Statistics","code":"BS-M301"}],"CSDS":[{"name":"Analog and Digital Electronics","code":"ESC301"},{"name":"Data Structure & Algorithms","code":"PCC-CS301"},{"name":"Computer Organization","code":"PCC-CS302"},{"name":"Introduction to Data Science","code":"PCC-DS301"},{"name":"Mathematics-III","code":"BSC 301"},{"name":"Economics for Engineers","code":"HSMC 301"}],"ME":[{"name":"Engineering Mechanics","code":"ES-ME301"},{"name":"Basic Electronics Engineering","code":"ES-ECE301"},{"name":"Mathematics","code":"BS-M301"},{"name":"Biology","code":"BS-BIO301"},{"name":"Thermodynamics","code":"PC-ME301"},{"name":"Manufacturing Processes","code":"PC-ME302"}]}}}